inkpython/__init__.py
inkpython/cli.py
inkpython/runtime.py
inkpython/engine/__init__.py
inkpython/engine/call_stack.py
inkpython/engine/choice.py
inkpython/engine/choice_point.py
inkpython/engine/container.py
inkpython/engine/control_command.py
inkpython/engine/debug.py
inkpython/engine/debug_metadata.py
inkpython/engine/divert.py
inkpython/engine/error.py
inkpython/engine/flow.py
inkpython/engine/glue.py
inkpython/engine/inamed_content.py
inkpython/engine/ink_list.py
inkpython/engine/json_serialisation.py
inkpython/engine/list_definition.py
inkpython/engine/list_definitions_origin.py
inkpython/engine/native_function_call.py
inkpython/engine/null_exception.py
inkpython/engine/object.py
inkpython/engine/path.py
inkpython/engine/pointer.py
inkpython/engine/prng.py
inkpython/engine/push_pop.py
inkpython/engine/search_result.py
inkpython/engine/simple_json.py
inkpython/engine/state_patch.py
inkpython/engine/stop_watch.py
inkpython/engine/story.py
inkpython/engine/story_exception.py
inkpython/engine/story_state.py
inkpython/engine/string_builder.py
inkpython/engine/tag.py
inkpython/engine/try_get_result.py
inkpython/engine/type_assertion.py
inkpython/engine/value.py
inkpython/engine/variable_assignment.py
inkpython/engine/variable_reference.py
inkpython/engine/variables_state.py
inkpython/engine/void.py
inkpython-0.1.0.dist-info/licenses/LICENSE
inkpython-0.1.0.dist-info/METADATA
inkpython-0.1.0.dist-info/WHEEL
inkpython-0.1.0.dist-info/entry_points.txt
inkpython-0.1.0.dist-info/top_level.txt
inkpython-0.1.0.dist-info/RECORD
